suscape/data/__init__.py
suscape/data/box.py
suscape/data/ego_pose.py
suscape/data/lidar_pointcloud.py
suscape/data/radar.py
suscape/dataset/__init__.py
suscape/dataset/bin_pcd_reader.py
suscape/dataset/dataset.py
suscape/dataset/suscape_dataset.py
suscape/eval/__init__.py
suscape/eval/detection_2d/__init__.py
suscape/eval/detection_2d/det_eval_2d_util.py
suscape/eval/detection_2d/evaluate_2d.py
suscape/eval/detection_3d/__init__.py
suscape/eval/detection_3d/accumulate.py
suscape/eval/detection_3d/evaluate.py
suscape/eval/detection_3d/evaluate_3d.py
suscape/eval/detection_3d/get_iou.py
suscape/eval/detection_3d/utils.py
suscape/eval/segmentation/__init__.py
suscape/eval/segmentation/eval_seg.py
suscape/eval/segmentation/seg_utils.py
suscape/tools/__init__.py
suscape/tools/gen_semantic_png.py
suscape/tools/sus3d_to_kitti/__init__.py
suscape/tools/sus3d_to_kitti/sus2kitti.py
suscape/tools/sus3d_to_kitti/kitti_package/__init__.py
suscape/tools/sus3d_to_kitti/kitti_package/kitti_calibration.py
suscape/tools/sus3d_to_kitti/kitti_package/kitti_util.py
suscape/utils/__init__.py
suscape/utils/calibration.py
suscape/utils/common_utils.py
suscape/utils/draw_gt.py
suscape/utils/obj_color.py
suscape/utils/parse_pcd.py
suscape_devkit-0.0.1.dist-info/LICENSE
suscape_devkit-0.0.1.dist-info/METADATA
suscape_devkit-0.0.1.dist-info/WHEEL
suscape_devkit-0.0.1.dist-info/top_level.txt
suscape_devkit-0.0.1.dist-info/RECORD
