Metadata-Version: 2.1
Name: suscape-devkit
Version: 0.0.1
Summary: suscape dataset devkit
Author-email: naurril <naurril@gmail.com>
Project-URL: Homepage, https://suscape.com
Project-URL: Bug Tracker, https://github.com/sustech-isus/suscape-devkit/issues
Classifier: Programming Language :: Python :: 3
Classifier: License :: OSI Approved :: MIT License
Classifier: Operating System :: OS Independent
Requires-Python: >=3.7
License-File: LICENSE
